[{"name":"abstract class WriteCompilerPluginsSettings : DefaultTask","description":"io.spine.tools.core.jvm.gradle.plugins.WriteCompilerPluginsSettings","location":"gradle-plugins/io.spine.tools.core.jvm.gradle.plugins/-write-compiler-plugins-settings/index.html","searchKeys":["WriteCompilerPluginsSettings","abstract class WriteCompilerPluginsSettings : DefaultTask","io.spine.tools.core.jvm.gradle.plugins.WriteCompilerPluginsSettings"]},{"name":"abstract val settingsDir: DirectoryProperty","description":"io.spine.tools.core.jvm.gradle.plugins.WriteCompilerPluginsSettings.settingsDir","location":"gradle-plugins/io.spine.tools.core.jvm.gradle.plugins/-write-compiler-plugins-settings/settings-dir.html","searchKeys":["settingsDir","abstract val settingsDir: DirectoryProperty","io.spine.tools.core.jvm.gradle.plugins.WriteCompilerPluginsSettings.settingsDir"]},{"name":"class CleaningPlugin : Plugin<Project> ","description":"io.spine.tools.core.jvm.gradle.plugins.CleaningPlugin","location":"gradle-plugins/io.spine.tools.core.jvm.gradle.plugins/-cleaning-plugin/index.html","searchKeys":["CleaningPlugin","class CleaningPlugin : Plugin<Project> ","io.spine.tools.core.jvm.gradle.plugins.CleaningPlugin"]},{"name":"class CoreJvmPlugin : LibraryPlugin<CoreJvmOptions> ","description":"io.spine.tools.core.jvm.gradle.plugins.CoreJvmPlugin","location":"gradle-plugins/io.spine.tools.core.jvm.gradle.plugins/-core-jvm-plugin/index.html","searchKeys":["CoreJvmPlugin","class CoreJvmPlugin : LibraryPlugin<CoreJvmOptions> ","io.spine.tools.core.jvm.gradle.plugins.CoreJvmPlugin"]},{"name":"const val ID: String","description":"io.spine.tools.core.jvm.gradle.plugins.CoreJvmPlugin.Companion.ID","location":"gradle-plugins/io.spine.tools.core.jvm.gradle.plugins/-core-jvm-plugin/-companion/-i-d.html","searchKeys":["ID","const val ID: String","io.spine.tools.core.jvm.gradle.plugins.CoreJvmPlugin.Companion.ID"]},{"name":"const val id: String","description":"io.spine.tools.core.jvm.gradle.plugins.KspGradlePlugin.id","location":"gradle-plugins/io.spine.tools.core.jvm.gradle.plugins/-ksp-gradle-plugin/id.html","searchKeys":["id","const val id: String","io.spine.tools.core.jvm.gradle.plugins.KspGradlePlugin.id"]},{"name":"const val id: String","description":"io.spine.tools.core.jvm.gradle.plugins.ProtobufGradlePlugin.id","location":"gradle-plugins/io.spine.tools.core.jvm.gradle.plugins/-protobuf-gradle-plugin/id.html","searchKeys":["id","const val id: String","io.spine.tools.core.jvm.gradle.plugins.ProtobufGradlePlugin.id"]},{"name":"constructor()","description":"io.spine.tools.core.jvm.gradle.plugins.CleaningPlugin.CleaningPlugin","location":"gradle-plugins/io.spine.tools.core.jvm.gradle.plugins/-cleaning-plugin/-cleaning-plugin.html","searchKeys":["CleaningPlugin","constructor()","io.spine.tools.core.jvm.gradle.plugins.CleaningPlugin.CleaningPlugin"]},{"name":"constructor()","description":"io.spine.tools.core.jvm.gradle.plugins.CoreJvmPlugin.CoreJvmPlugin","location":"gradle-plugins/io.spine.tools.core.jvm.gradle.plugins/-core-jvm-plugin/-core-jvm-plugin.html","searchKeys":["CoreJvmPlugin","constructor()","io.spine.tools.core.jvm.gradle.plugins.CoreJvmPlugin.CoreJvmPlugin"]},{"name":"constructor()","description":"io.spine.tools.core.jvm.gradle.plugins.WriteCompilerPluginsSettings.WriteCompilerPluginsSettings","location":"gradle-plugins/io.spine.tools.core.jvm.gradle.plugins/-write-compiler-plugins-settings/-write-compiler-plugins-settings.html","searchKeys":["WriteCompilerPluginsSettings","constructor()","io.spine.tools.core.jvm.gradle.plugins.WriteCompilerPluginsSettings.WriteCompilerPluginsSettings"]},{"name":"fun writeFiles()","description":"io.spine.tools.core.jvm.gradle.plugins.WriteCompilerPluginsSettings.writeFiles","location":"gradle-plugins/io.spine.tools.core.jvm.gradle.plugins/-write-compiler-plugins-settings/write-files.html","searchKeys":["writeFiles","fun writeFiles()","io.spine.tools.core.jvm.gradle.plugins.WriteCompilerPluginsSettings.writeFiles"]},{"name":"object Companion","description":"io.spine.tools.core.jvm.gradle.plugins.CoreJvmPlugin.Companion","location":"gradle-plugins/io.spine.tools.core.jvm.gradle.plugins/-core-jvm-plugin/-companion/index.html","searchKeys":["Companion","object Companion","io.spine.tools.core.jvm.gradle.plugins.CoreJvmPlugin.Companion"]},{"name":"object KotlinGradlePlugin","description":"io.spine.tools.core.jvm.gradle.plugins.KotlinGradlePlugin","location":"gradle-plugins/io.spine.tools.core.jvm.gradle.plugins/-kotlin-gradle-plugin/index.html","searchKeys":["KotlinGradlePlugin","object KotlinGradlePlugin","io.spine.tools.core.jvm.gradle.plugins.KotlinGradlePlugin"]},{"name":"object KspGradlePlugin","description":"io.spine.tools.core.jvm.gradle.plugins.KspGradlePlugin","location":"gradle-plugins/io.spine.tools.core.jvm.gradle.plugins/-ksp-gradle-plugin/index.html","searchKeys":["KspGradlePlugin","object KspGradlePlugin","io.spine.tools.core.jvm.gradle.plugins.KspGradlePlugin"]},{"name":"object Meta : LazyMeta","description":"io.spine.tools.core.jvm.gradle.plugins.Meta","location":"gradle-plugins/io.spine.tools.core.jvm.gradle.plugins/-meta/index.html","searchKeys":["Meta","object Meta : LazyMeta","io.spine.tools.core.jvm.gradle.plugins.Meta"]},{"name":"object ProtobufGradlePlugin","description":"io.spine.tools.core.jvm.gradle.plugins.ProtobufGradlePlugin","location":"gradle-plugins/io.spine.tools.core.jvm.gradle.plugins/-protobuf-gradle-plugin/index.html","searchKeys":["ProtobufGradlePlugin","object ProtobufGradlePlugin","io.spine.tools.core.jvm.gradle.plugins.ProtobufGradlePlugin"]},{"name":"open override fun apply(project: Project)","description":"io.spine.tools.core.jvm.gradle.plugins.CleaningPlugin.apply","location":"gradle-plugins/io.spine.tools.core.jvm.gradle.plugins/-cleaning-plugin/apply.html","searchKeys":["apply","open override fun apply(project: Project)","io.spine.tools.core.jvm.gradle.plugins.CleaningPlugin.apply"]},{"name":"open override fun apply(project: Project)","description":"io.spine.tools.core.jvm.gradle.plugins.CoreJvmPlugin.apply","location":"gradle-plugins/io.spine.tools.core.jvm.gradle.plugins/-core-jvm-plugin/apply.html","searchKeys":["apply","open override fun apply(project: Project)","io.spine.tools.core.jvm.gradle.plugins.CoreJvmPlugin.apply"]},{"name":"val artifact: MavenArtifact","description":"io.spine.tools.core.jvm.gradle.plugins.Meta.artifact","location":"gradle-plugins/io.spine.tools.core.jvm.gradle.plugins/-meta/artifact.html","searchKeys":["artifact","val artifact: MavenArtifact","io.spine.tools.core.jvm.gradle.plugins.Meta.artifact"]},{"name":"val version: String","description":"io.spine.tools.core.jvm.gradle.plugins.KotlinGradlePlugin.version","location":"gradle-plugins/io.spine.tools.core.jvm.gradle.plugins/-kotlin-gradle-plugin/version.html","searchKeys":["version","val version: String","io.spine.tools.core.jvm.gradle.plugins.KotlinGradlePlugin.version"]},{"name":"val version: String","description":"io.spine.tools.core.jvm.gradle.plugins.KspGradlePlugin.version","location":"gradle-plugins/io.spine.tools.core.jvm.gradle.plugins/-ksp-gradle-plugin/version.html","searchKeys":["version","val version: String","io.spine.tools.core.jvm.gradle.plugins.KspGradlePlugin.version"]},{"name":"val version: String","description":"io.spine.tools.core.jvm.gradle.plugins.ProtobufGradlePlugin.version","location":"gradle-plugins/io.spine.tools.core.jvm.gradle.plugins/-protobuf-gradle-plugin/version.html","searchKeys":["version","val version: String","io.spine.tools.core.jvm.gradle.plugins.ProtobufGradlePlugin.version"]}]